variational/__init__.py
variational/auth.py
variational/client.py
variational/models.py
variational/paginate.py
variational/permit.py
variational/polling.py
variational/rounding.py
variational/wrappers.py
variational-0.6.0.dist-info/METADATA
variational-0.6.0.dist-info/WHEEL
variational-0.6.0.dist-info/licenses/LICENSE
variational-0.6.0.dist-info/RECORD
