Metadata-Version: 2.4
Name: variational
Version: 0.6.0
Summary: Variational Reference SDK
Project-URL: Homepage, https://variational.io
Project-URL: Documentation, https://docs.variational.io/for-developers/api
Project-URL: Repository, https://github.com/variational-research/variational-sdk-python/
Project-URL: Issues, https://github.com/variational-research/variational-sdk-python/issues
Author-email: Variational Research <hello@variational.io>
License-File: LICENSE
Classifier: Intended Audience :: Developers
Classifier: Intended Audience :: Financial and Insurance Industry
Classifier: License :: OSI Approved :: MIT License
Classifier: Operating System :: OS Independent
Classifier: Programming Language :: Python :: 3
Classifier: Programming Language :: Python :: 3.11
Classifier: Programming Language :: Python :: 3.12
Requires-Python: >=3.11
Requires-Dist: brotli>=1.0
Requires-Dist: eth-account>=0.11
Requires-Dist: requests>=2.12
